LICENSE
MANIFEST.in
README.md
setup.py
django_export_csv/__init__.py
django_export_csv/function.py
django_export_csv/mixin.py
django_export_csv/utils.py
django_export_csv.egg-info/PKG-INFO
django_export_csv.egg-info/SOURCES.txt
django_export_csv.egg-info/dependency_links.txt
django_export_csv.egg-info/requires.txt
django_export_csv.egg-info/top_level.txt
tests/core/__init__.py
tests/core/data_init.py
tests/core/models.py
tests/core/settings.py
tests/core/urls.py
tests/core/views.py
tests/core/migrations/0001_initial.py
tests/core/migrations/__init__.py
tests/core/tests/__init__.py
tests/core/tests/tests_request.py
tests/core/tests/tests_utils.py