Metadata-Version: 1.1
Name: django-export-csv
Version: 0.1.3.1
Summary: A CSV exporter for Django, this tool create a shortcut to render a queryset to a CSV steaming HTTP response.
Home-page: https://github.com/oddcc/django-export-csv
Author: oddcc
Author-email: skycc71640@gmail.com
License: MIT License
Keywords: django,csv,export,queryset
Platform: UNKNOWN
Classifier: Development Status :: 4 - Beta
Classifier: Intended Audience :: Developers
Classifier: Programming Language :: Python
Classifier: Environment :: Plugins
Classifier: Framework :: Django
Classifier: License :: OSI Approved :: GNU General Public License (GPL)
